{
  "id": 2379,
  "jsonrpc": "2.0",
  "result": [
    {
      "event_id": 25511046,
      "market_has_param": false,
      "market_id": 784270465,
      "market_name": "Победа в матче",
      "market_order": "00700001000100000000",
      "market_suspend": false,
      "market_template_id": 3,
      "market_template_view_id": 1,
      "market_template_view_schema": null,
      "market_template_weigh": 10,
      "outcomes": [
        {
          "outcome_coef": 1.09,
          "outcome_id": 2041749025,
          "outcome_name": "Абакар Джалилов",
          "outcome_param": null,
          "outcome_perc_stat": 100.0,
          "outcome_short_name": "1",
          "outcome_tag": null,
          "outcome_tl_header_name": null,
          "outcome_tl_left_name": null,
          "outcome_type_id": 259,
          "outcome_visible": true,
          "participant_number": 1
        },
        {
          "outcome_coef": 6.4,
          "outcome_id": 2041749026,
          "outcome_name": "Николай Широков",
          "outcome_param": null,
          "outcome_perc_stat": 0.0,
          "outcome_short_name": "2",
          "outcome_tag": null,
          "outcome_tl_header_name": null,
          "outcome_tl_left_name": null,
          "outcome_type_id": 260,
          "outcome_visible": true,
          "participant_number": 2
        }
      ],
      "result_type_id": 1,
      "result_type_name": "Основное время",
      "result_type_short_name": "ОВ",
      "result_type_weigh": 1,
      "service_id": 1,
      "sport_id": 2
    },
    {
      "event_id": 25511046,
      "market_has_param": false,
      "market_id": 784290002,
      "market_name": "Победитель сета",
      "market_order": "00800001000100000000",
      "market_suspend": false,
      "market_template_id": 680,
      "market_template_view_id": 1,
      "market_template_view_schema": null,
      "market_template_weigh": 10,
      "outcomes": [
        {
          "outcome_coef": 1.41,
          "outcome_id": 2041807762,
          "outcome_name": "Абакар Джалилов",
          "outcome_param": null,
          "outcome_perc_stat": 0.0,
          "outcome_short_name": "1",
          "outcome_tag": null,
          "outcome_tl_header_name": null,
          "outcome_tl_left_name": null,
          "outcome_type_id": 259,
          "outcome_visible": true,
          "participant_number": 1
        },
        {
          "outcome_coef": 2.73,
          "outcome_id": 2041807763,
          "outcome_name": "Николай Широков",
          "outcome_param": null,
          "outcome_perc_stat": 0.0,
          "outcome_short_name": "2",
          "outcome_tag": null,
          "outcome_tl_header_name": null,
          "outcome_tl_left_name": null,
          "outcome_type_id": 260,
          "outcome_visible": true,
          "participant_number": 2
        }
      ],
      "result_type_id": 83,
      "result_type_name": "4 Сет",
      "result_type_short_name": "C4",
      "result_type_weigh": 5,
      "service_id": 1,
      "sport_id": 2
    },
    {
      "event_id": 25511046,
      "market_has_param": true,
      "market_id": 784291337,
      "market_name": "Кто выиграет 3-ий гейм?",
      "market_order": "01500001003100000000",
      "market_suspend": false,
      "market_template_id": 800,
      "market_template_view_id": 1,
      "market_template_view_schema": null,
      "market_template_weigh": 15,
      "outcomes": [
        {
          "outcome_coef": 2.81,
          "outcome_id": 2041812135,
          "outcome_name": "Абакар Джалилов",
          "outcome_param": null,
          "outcome_perc_stat": 0.0,
          "outcome_short_name": "1",
          "outcome_tag": null,
          "outcome_tl_header_name": null,
          "outcome_tl_left_name": null,
          "outcome_type_id": 259,
          "outcome_visible": true,
          "participant_number": 1
        },
        {
          "outcome_coef": 1.39,
          "outcome_id": 2041812136,
          "outcome_name": "Николай Широков",
          "outcome_param": null,
          "outcome_perc_stat": 0.0,
          "outcome_short_name": "2",
          "outcome_tag": null,
          "outcome_tl_header_name": null,
          "outcome_tl_left_name": null,
          "outcome_type_id": 260,
          "outcome_visible": true,
          "participant_number": 2
        }
      ],
      "result_type_id": 83,
      "result_type_name": "4 Сет",
      "result_type_short_name": "C4",
      "result_type_weigh": 5,
      "service_id": 1,
      "sport_id": 2
    },
    {
      "event_id": 25511046,
      "market_has_param": true,
      "market_id": 784291537,
      "market_name": "Кто выиграет 4-ый гейм?",
      "market_order": "01500001004100000000",
      "market_suspend": false,
      "market_template_id": 800,
      "market_template_view_id": 1,
      "market_template_view_schema": null,
      "market_template_weigh": 15,
      "outcomes": [
        {
          "outcome_coef": 1.2,
          "outcome_id": 2041812648,
          "outcome_name": "Абакар Джалилов",
          "outcome_param": null,
          "outcome_perc_stat": 0.0,
          "outcome_short_name": "1",
          "outcome_tag": null,
          "outcome_tl_header_name": null,
          "outcome_tl_left_name": null,
          "outcome_type_id": 259,
          "outcome_visible": true,
          "participant_number": 1
        },
        {
          "outcome_coef": 4.1,
          "outcome_id": 2041812649,
          "outcome_name": "Николай Широков",
          "outcome_param": null,
          "outcome_perc_stat": 0.0,
          "outcome_short_name": "2",
          "outcome_tag": null,
          "outcome_tl_header_name": null,
          "outcome_tl_left_name": null,
          "outcome_type_id": 260,
          "outcome_visible": true,
          "participant_number": 2
        }
      ],
      "result_type_id": 83,
      "result_type_name": "4 Сет",
      "result_type_short_name": "C4",
      "result_type_weigh": 5,
      "service_id": 1,
      "sport_id": 2
    },
    {
      "event_id": 25511046,
      "market_has_param": true,
      "market_id": 784291419,
      "market_name": "Будет ли 40-40 в 4-ом гейме",
      "market_order": "02000001004100000000",
      "market_suspend": false,
      "market_template_id": 1193,
      "market_template_view_id": 1,
      "market_template_view_schema": null,
      "market_template_weigh": 20,
      "outcomes": [
        {
          "outcome_coef": 3.3,
          "outcome_id": 2041812333,
          "outcome_name": "Да (4)",
          "outcome_param": "4",
          "outcome_perc_stat": 0.0,
          "outcome_short_name": "Да (4)",
          "outcome_tag": null,
          "outcome_tl_header_name": null,
          "outcome_tl_left_name": null,
          "outcome_type_id": 20,
          "outcome_visible": true,
          "participant_number": null
        },
        {
          "outcome_coef": 1.28,
          "outcome_id": 2041812334,
          "outcome_name": "Нет (4)",
          "outcome_param": "4",
          "outcome_perc_stat": 0.0,
          "outcome_short_name": "Нет (4)",
          "outcome_tag": null,
          "outcome_tl_header_name": null,
          "outcome_tl_left_name": null,
          "outcome_type_id": 21,
          "outcome_visible": true,
          "participant_number": null
        }
      ],
      "result_type_id": 83,
      "result_type_name": "4 Сет",
      "result_type_short_name": "C4",
      "result_type_weigh": 5,
      "service_id": 1,
      "sport_id": 2
    },
    {
      "event_id": 25511046,
      "market_has_param": true,
      "market_id": 784291571,
      "market_name": "Будет ли 40-40 в 5-ом гейме",
      "market_order": "02000001005100000000",
      "market_suspend": false,
      "market_template_id": 1193,
      "market_template_view_id": 1,
      "market_template_view_schema": null,
      "market_template_weigh": 20,
      "outcomes": [
        {
          "outcome_coef": 2.92,
          "outcome_id": 2041812742,
          "outcome_name": "Да (5)",
          "outcome_param": "5",
          "outcome_perc_stat": 0.0,
          "outcome_short_name": "Да (5)",
          "outcome_tag": null,
          "outcome_tl_header_name": null,
          "outcome_tl_left_name": null,
          "outcome_type_id": 20,
          "outcome_visible": true,
          "participant_number": null
        },
        {
          "outcome_coef": 1.35,
          "outcome_id": 2041812743,
          "outcome_name": "Нет (5)",
          "outcome_param": "5",
          "outcome_perc_stat": 0.0,
          "outcome_short_name": "Нет (5)",
          "outcome_tag": null,
          "outcome_tl_header_name": null,
          "outcome_tl_left_name": null,
          "outcome_type_id": 21,
          "outcome_visible": true,
          "participant_number": null
        }
      ],
      "result_type_id": 83,
      "result_type_name": "4 Сет",
      "result_type_short_name": "C4",
      "result_type_weigh": 5,
      "service_id": 1,
      "sport_id": 2
    },
    {
      "event_id": 25511046,
      "market_has_param": true,
      "market_id": 784291420,
      "market_name": "Точный счет 4-го гейма",
      "market_order": "02500001004100000000",
      "market_suspend": false,
      "market_template_id": 1192,
      "market_template_view_id": 5,
      "market_template_view_schema": null,
      "market_template_weigh": 25,
      "outcomes": [
        {
          "outcome_coef": 4.65,
          "outcome_id": 2041812335,
          "outcome_name": "П1 : 0",
          "outcome_param": "P1 : 0",
          "outcome_perc_stat": 0.0,
          "outcome_short_name": "П1 : 0",
          "outcome_tag": null,
          "outcome_tl_header_name": null,
          "outcome_tl_left_name": null,
          "outcome_type_id": 604,
          "outcome_visible": true,
          "participant_number": 1
        },
        {
          "outcome_coef": 20.0,
          "outcome_id": 2041812339,
          "outcome_name": "П2 : 0",
          "outcome_param": "P2 : 0",
          "outcome_perc_stat": 0.0,
          "outcome_short_name": "П2 : 0",
          "outcome_tag": null,
          "outcome_tl_header_name": null,
          "outcome_tl_left_name": null,
          "outcome_type_id": 608,
          "outcome_visible": true,
          "participant_number": 2
        },
        {
          "outcome_coef": 3.2,
          "outcome_id": 2041812336,
          "outcome_name": "П1 : 15",
          "outcome_param": "P1 : 15",
          "outcome_perc_stat": 0.0,
          "outcome_short_name": "П1 : 15",
          "outcome_tag": null,
          "outcome_tl_header_name": null,
          "outcome_tl_left_name": null,
          "outcome_type_id": 605,
          "outcome_visible": true,
          "participant_number": 1
        },
        {
          "outcome_coef": 15.5,
          "outcome_id": 2041812340,
          "outcome_name": "П2 : 15",
          "outcome_param": "P2 : 15",
          "outcome_perc_stat": 0.0,
          "outcome_short_name": "П2 : 15",
          "outcome_tag": null,
          "outcome_tl_header_name": null,
          "outcome_tl_left_name": null,
          "outcome_type_id": 609,
          "outcome_visible": true,
          "participant_number": 2
        },
        {
          "outcome_coef": 3.55,
          "outcome_id": 2041812337,
          "outcome_name": "П1 : 30",
          "outcome_param": "P1 : 30",
          "outcome_perc_stat": 0.0,
          "outcome_short_name": "П1 : 30",
          "outcome_tag": null,
          "outcome_tl_header_name": null,
          "outcome_tl_left_name": null,
          "outcome_type_id": 606,
          "outcome_visible": true,
          "participant_number": 1
        },
        {
          "outcome_coef": 11.0,
          "outcome_id": 2041812341,
          "outcome_name": "П2 : 30",
          "outcome_param": "P2 : 30",
          "outcome_perc_stat": 0.0,
          "outcome_short_name": "П2 : 30",
          "outcome_tag": null,
          "outcome_tl_header_name": null,
          "outcome_tl_left_name": null,
          "outcome_type_id": 610,
          "outcome_visible": true,
          "participant_number": 2
        },
        {
          "outcome_coef": 4.2,
          "outcome_id": 2041812338,
          "outcome_name": "П1 : 40",
          "outcome_param": "P1 : 40",
          "outcome_perc_stat": 0.0,
          "outcome_short_name": "П1 : 40",
          "outcome_tag": null,
          "outcome_tl_header_name": null,
          "outcome_tl_left_name": null,
          "outcome_type_id": 607,
          "outcome_visible": true,
          "participant_number": 1
        },
        {
          "outcome_coef": 12.5,
          "outcome_id": 2041812342,
          "outcome_name": "П2 : 40",
          "outcome_param": "P2 : 40",
          "outcome_perc_stat": 0.0,
          "outcome_short_name": "П2 : 40",
          "outcome_tag": null,
          "outcome_tl_header_name": null,
          "outcome_tl_left_name": null,
          "outcome_type_id": 611,
          "outcome_visible": true,
          "participant_number": 2
        }
      ],
      "result_type_id": 83,
      "result_type_name": "4 Сет",
      "result_type_short_name": "C4",
      "result_type_weigh": 5,
      "service_id": 1,
      "sport_id": 2
    },
    {
      "event_id": 25511046,
      "market_has_param": true,
      "market_id": 784291572,
      "market_name": "Точный счет 5-го гейма",
      "market_order": "02500001005100000000",
      "market_suspend": false,
      "market_template_id": 1192,
      "market_template_view_id": 5,
      "market_template_view_schema": null,
      "market_template_weigh": 25,
      "outcomes": [
        {
          "outcome_coef": 19.5,
          "outcome_id": 2041812744,
          "outcome_name": "П1 : 0",
          "outcome_param": "P1 : 0",
          "outcome_perc_stat": 0.0,
          "outcome_short_name": "П1 : 0",
          "outcome_tag": null,
          "outcome_tl_header_name": null,
          "outcome_tl_left_name": null,
          "outcome_type_id": 604,
          "outcome_visible": true,
          "participant_number": 1
        },
        {
          "outcome_coef": 6.9,
          "outcome_id": 2041812748,
          "outcome_name": "П2 : 0",
          "outcome_param": "P2 : 0",
          "outcome_perc_stat": 0.0,
          "outcome_short_name": "П2 : 0",
          "outcome_tag": null,
          "outcome_tl_header_name": null,
          "outcome_tl_left_name": null,
          "outcome_type_id": 608,
          "outcome_visible": true,
          "participant_number": 2
        },
        {
          "outcome_coef": 10.5,
          "outcome_id": 2041812745,
          "outcome_name": "П1 : 15",
          "outcome_param": "P1 : 15",
          "outcome_perc_stat": 0.0,
          "outcome_short_name": "П1 : 15",
          "outcome_tag": null,
          "outcome_tl_header_name": null,
          "outcome_tl_left_name": null,
          "outcome_type_id": 605,
          "outcome_visible": true,
          "participant_number": 1
        },
        {
          "outcome_coef": 4.1,
          "outcome_id": 2041812749,
          "outcome_name": "П2 : 15",
          "outcome_param": "P2 : 15",
          "outcome_perc_stat": 0.0,
          "outcome_short_name": "П2 : 15",
          "outcome_tag": null,
          "outcome_tl_header_name": null,
          "outcome_tl_left_name": null,
          "outcome_type_id": 609,
          "outcome_visible": true,
          "participant_number": 2
        },
        {
          "outcome_coef": 7.4,
          "outcome_id": 2041812746,
          "outcome_name": "П1 : 30",
          "outcome_param": "P1 : 30",
          "outcome_perc_stat": 0.0,
          "outcome_short_name": "П1 : 30",
          "outcome_tag": null,
          "outcome_tl_header_name": null,
          "outcome_tl_left_name": null,
          "outcome_type_id": 606,
          "outcome_visible": true,
          "participant_number": 1
        },
        {
          "outcome_coef": 3.9,
          "outcome_id": 2041812750,
          "outcome_name": "П2 : 30",
          "outcome_param": "P2 : 30",
          "outcome_perc_stat": 0.0,
          "outcome_short_name": "П2 : 30",
          "outcome_tag": null,
          "outcome_tl_header_name": null,
          "outcome_tl_left_name": null,
          "outcome_type_id": 610,
          "outcome_visible": true,
          "participant_number": 2
        },
        {
          "outcome_coef": 7.8,
          "outcome_id": 2041812747,
          "outcome_name": "П1 : 40",
          "outcome_param": "P1 : 40",
          "outcome_perc_stat": 0.0,
          "outcome_short_name": "П1 : 40",
          "outcome_tag": null,
          "outcome_tl_header_name": null,
          "outcome_tl_left_name": null,
          "outcome_type_id": 607,
          "outcome_visible": true,
          "participant_number": 1
        },
        {
          "outcome_coef": 4.1,
          "outcome_id": 2041812751,
          "outcome_name": "П2 : 40",
          "outcome_param": "P2 : 40",
          "outcome_perc_stat": 0.0,
          "outcome_short_name": "П2 : 40",
          "outcome_tag": null,
          "outcome_tl_header_name": null,
          "outcome_tl_left_name": null,
          "outcome_type_id": 611,
          "outcome_visible": true,
          "participant_number": 2
        }
      ],
      "result_type_id": 83,
      "result_type_name": "4 Сет",
      "result_type_short_name": "C4",
      "result_type_weigh": 5,
      "service_id": 1,
      "sport_id": 2
    },
    {
      "event_id": 25511046,
      "market_has_param": true,
      "market_id": 784289986,
      "market_name": "Кто выиграет первое очко в 4-ом гейме",
      "market_order": "03000001004100000000",
      "market_suspend": false,
      "market_template_id": 1195,
      "market_template_view_id": 1,
      "market_template_view_schema": null,
      "market_template_weigh": 30,
      "outcomes": [
        {
          "outcome_coef": 1.49,
          "outcome_id": 2041807718,
          "outcome_name": "Абакар Джалилов",
          "outcome_param": null,
          "outcome_perc_stat": 0.0,
          "outcome_short_name": "1",
          "outcome_tag": null,
          "outcome_tl_header_name": null,
          "outcome_tl_left_name": null,
          "outcome_type_id": 259,
          "outcome_visible": true,
          "participant_number": 1
        },
        {
          "outcome_coef": 2.5,
          "outcome_id": 2041807719,
          "outcome_name": "Николай Широков",
          "outcome_param": null,
          "outcome_perc_stat": 0.0,
          "outcome_short_name": "2",
          "outcome_tag": null,
          "outcome_tl_header_name": null,
          "outcome_tl_left_name": null,
          "outcome_type_id": 260,
          "outcome_visible": true,
          "participant_number": 2
        }
      ],
      "result_type_id": 83,
      "result_type_name": "4 Сет",
      "result_type_short_name": "C4",
      "result_type_weigh": 5,
      "service_id": 1,
      "sport_id": 2
    },
    {
      "event_id": 25511046,
      "market_has_param": true,
      "market_id": 784291421,
      "market_name": "Кто выиграет первое очко в 5-ом гейме",
      "market_order": "03000001005100000000",
      "market_suspend": false,
      "market_template_id": 1195,
      "market_template_view_id": 1,
      "market_template_view_schema": null,
      "market_template_weigh": 30,
      "outcomes": [
        {
          "outcome_coef": 2.2,
          "outcome_id": 2041812343,
          "outcome_name": "Абакар Джалилов",
          "outcome_param": null,
          "outcome_perc_stat": 0.0,
          "outcome_short_name": "1",
          "outcome_tag": null,
          "outcome_tl_header_name": null,
          "outcome_tl_left_name": null,
          "outcome_type_id": 259,
          "outcome_visible": true,
          "participant_number": 1
        },
        {
          "outcome_coef": 1.59,
          "outcome_id": 2041812344,
          "outcome_name": "Николай Широков",
          "outcome_param": null,
          "outcome_perc_stat": 0.0,
          "outcome_short_name": "2",
          "outcome_tag": null,
          "outcome_tl_header_name": null,
          "outcome_tl_left_name": null,
          "outcome_type_id": 260,
          "outcome_visible": true,
          "participant_number": 2
        }
      ],
      "result_type_id": 83,
      "result_type_name": "4 Сет",
      "result_type_short_name": "C4",
      "result_type_weigh": 5,
      "service_id": 1,
      "sport_id": 2
    },
    {
      "event_id": 25511046,
      "market_has_param": true,
      "market_id": 784291573,
      "market_name": "Кто выиграет первое очко в 6-ом гейме",
      "market_order": "03000001006100000000",
      "market_suspend": false,
      "market_template_id": 1195,
      "market_template_view_id": 1,
      "market_template_view_schema": null,
      "market_template_weigh": 30,
      "outcomes": [
        {
          "outcome_coef": 1.49,
          "outcome_id": 2041812752,
          "outcome_name": "Абакар Джалилов",
          "outcome_param": null,
          "outcome_perc_stat": 0.0,
          "outcome_short_name": "1",
          "outcome_tag": null,
          "outcome_tl_header_name": null,
          "outcome_tl_left_name": null,
          "outcome_type_id": 259,
          "outcome_visible": true,
          "participant_number": 1
        },
        {
          "outcome_coef": 2.5,
          "outcome_id": 2041812753,
          "outcome_name": "Николай Широков",
          "outcome_param": null,
          "outcome_perc_stat": 0.0,
          "outcome_short_name": "2",
          "outcome_tag": null,
          "outcome_tl_header_name": null,
          "outcome_tl_left_name": null,
          "outcome_type_id": 260,
          "outcome_visible": true,
          "participant_number": 2
        }
      ],
      "result_type_id": 83,
      "result_type_name": "4 Сет",
      "result_type_short_name": "C4",
      "result_type_weigh": 5,
      "service_id": 1,
      "sport_id": 2
    },
    {
      "event_id": 25511046,
      "market_has_param": true,
      "market_id": 784291566,
      "market_name": "Кто выиграет 2 очко в 3 гейме",
      "market_order": "03500001002100000000",
      "market_suspend": false,
      "market_template_id": 1208,
      "market_template_view_id": 1,
      "market_template_view_schema": null,
      "market_template_weigh": 35,
      "outcomes": [
        {
          "outcome_coef": 2.2,
          "outcome_id": 2041812732,
          "outcome_name": "Абакар Джалилов",
          "outcome_param": null,
          "outcome_perc_stat": 0.0,
          "outcome_short_name": "1",
          "outcome_tag": null,
          "outcome_tl_header_name": null,
          "outcome_tl_left_name": null,
          "outcome_type_id": 259,
          "outcome_visible": true,
          "participant_number": 1
        },
        {
          "outcome_coef": 1.59,
          "outcome_id": 2041812733,
          "outcome_name": "Николай Широков",
          "outcome_param": null,
          "outcome_perc_stat": 0.0,
          "outcome_short_name": "2",
          "outcome_tag": null,
          "outcome_tl_header_name": null,
          "outcome_tl_left_name": null,
          "outcome_type_id": 260,
          "outcome_visible": true,
          "participant_number": 2
        }
      ],
      "result_type_id": 83,
      "result_type_name": "4 Сет",
      "result_type_short_name": "C4",
      "result_type_weigh": 5,
      "service_id": 1,
      "sport_id": 2
    },
    {
      "event_id": 25511046,
      "market_has_param": true,
      "market_id": 784291567,
      "market_name": "Кто выиграет 3 очко в 3 гейме",
      "market_order": "03500001003100000000",
      "market_suspend": false,
      "market_template_id": 1208,
      "market_template_view_id": 1,
      "market_template_view_schema": null,
      "market_template_weigh": 35,
      "outcomes": [
        {
          "outcome_coef": 2.2,
          "outcome_id": 2041812734,
          "outcome_name": "Абакар Джалилов",
          "outcome_param": null,
          "outcome_perc_stat": 0.0,
          "outcome_short_name": "1",
          "outcome_tag": null,
          "outcome_tl_header_name": null,
          "outcome_tl_left_name": null,
          "outcome_type_id": 259,
          "outcome_visible": true,
          "participant_number": 1
        },
        {
          "outcome_coef": 1.59,
          "outcome_id": 2041812735,
          "outcome_name": "Николай Широков",
          "outcome_param": null,
          "outcome_perc_stat": 0.0,
          "outcome_short_name": "2",
          "outcome_tag": null,
          "outcome_tl_header_name": null,
          "outcome_tl_left_name": null,
          "outcome_type_id": 260,
          "outcome_visible": true,
          "participant_number": 2
        }
      ],
      "result_type_id": 83,
      "result_type_name": "4 Сет",
      "result_type_short_name": "C4",
      "result_type_weigh": 5,
      "service_id": 1,
      "sport_id": 2
    },
    {
      "event_id": 25511046,
      "market_has_param": true,
      "market_id": 784291568,
      "market_name": "Кто выиграет 4 очко в 3 гейме",
      "market_order": "03500001004100000000",
      "market_suspend": false,
      "market_template_id": 1208,
      "market_template_view_id": 1,
      "market_template_view_schema": null,
      "market_template_weigh": 35,
      "outcomes": [
        {
          "outcome_coef": 2.2,
          "outcome_id": 2041812736,
          "outcome_name": "Абакар Джалилов",
          "outcome_param": null,
          "outcome_perc_stat": 0.0,
          "outcome_short_name": "1",
          "outcome_tag": null,
          "outcome_tl_header_name": null,
          "outcome_tl_left_name": null,
          "outcome_type_id": 259,
          "outcome_visible": true,
          "participant_number": 1
        },
        {
          "outcome_coef": 1.59,
          "outcome_id": 2041812737,
          "outcome_name": "Николай Широков",
          "outcome_param": null,
          "outcome_perc_stat": 0.0,
          "outcome_short_name": "2",
          "outcome_tag": null,
          "outcome_tl_header_name": null,
          "outcome_tl_left_name": null,
          "outcome_type_id": 260,
          "outcome_visible": true,
          "participant_number": 2
        }
      ],
      "result_type_id": 83,
      "result_type_name": "4 Сет",
      "result_type_short_name": "C4",
      "result_type_weigh": 5,
      "service_id": 1,
      "sport_id": 2
    },
    {
      "event_id": 25511046,
      "market_has_param": true,
      "market_id": 784291569,
      "market_name": "Кто выиграет 5 очко в 3 гейме",
      "market_order": "03500001005100000000",
      "market_suspend": false,
      "market_template_id": 1208,
      "market_template_view_id": 1,
      "market_template_view_schema": null,
      "market_template_weigh": 35,
      "outcomes": [
        {
          "outcome_coef": 2.2,
          "outcome_id": 2041812738,
          "outcome_name": "Абакар Джалилов",
          "outcome_param": null,
          "outcome_perc_stat": 0.0,
          "outcome_short_name": "1",
          "outcome_tag": null,
          "outcome_tl_header_name": null,
          "outcome_tl_left_name": null,
          "outcome_type_id": 259,
          "outcome_visible": true,
          "participant_number": 1
        },
        {
          "outcome_coef": 1.59,
          "outcome_id": 2041812739,
          "outcome_name": "Николай Широков",
          "outcome_param": null,
          "outcome_perc_stat": 0.0,
          "outcome_short_name": "2",
          "outcome_tag": null,
          "outcome_tl_header_name": null,
          "outcome_tl_left_name": null,
          "outcome_type_id": 260,
          "outcome_visible": true,
          "participant_number": 2
        }
      ],
      "result_type_id": 83,
      "result_type_name": "4 Сет",
      "result_type_short_name": "C4",
      "result_type_weigh": 5,
      "service_id": 1,
      "sport_id": 2
    },
    {
      "event_id": 25511046,
      "market_has_param": true,
      "market_id": 784291570,
      "market_name": "Тотал Нечет / Чёт в 4 гейме",
      "market_order": "05500001004100000000",
      "market_suspend": false,
      "market_template_id": 1223,
      "market_template_view_id": 1,
      "market_template_view_schema": null,
      "market_template_weigh": 55,
      "outcomes": [
        {
          "outcome_coef": 2.97,
          "outcome_id": 2041812740,
          "outcome_name": "Нечет",
          "outcome_param": "Odd",
          "outcome_perc_stat": 0.0,
          "outcome_short_name": "Нечет",
          "outcome_tag": null,
          "outcome_tl_header_name": null,
          "outcome_tl_left_name": null,
          "outcome_type_id": 30,
          "outcome_visible": true,
          "participant_number": null
        },
        {
          "outcome_coef": 1.34,
          "outcome_id": 2041812741,
          "outcome_name": "Чет",
          "outcome_param": "Even",
          "outcome_perc_stat": 0.0,
          "outcome_short_name": "Чет",
          "outcome_tag": null,
          "outcome_tl_header_name": null,
          "outcome_tl_left_name": null,
          "outcome_type_id": 31,
          "outcome_visible": true,
          "participant_number": null
        }
      ],
      "result_type_id": 83,
      "result_type_name": "4 Сет",
      "result_type_short_name": "C4",
      "result_type_weigh": 5,
      "service_id": 1,
      "sport_id": 2
    },
    {
      "event_id": 25511046,
      "market_has_param": true,
      "market_id": 784291124,
      "market_name": "Фора по геймам",
      "market_order": "06000001000099850000",
      "market_suspend": false,
      "market_template_id": 690,
      "market_template_view_id": 1,
      "market_template_view_schema": null,
      "market_template_weigh": 60,
      "outcomes": [
        {
          "outcome_coef": 1.61,
          "outcome_id": 2041811500,
          "outcome_name": "Абакар Джалилов (-1.5) ",
          "outcome_param": "-1.5",
          "outcome_perc_stat": 0.0,
          "outcome_short_name": "1 (-1.5)",
          "outcome_tag": null,
          "outcome_tl_header_name": null,
          "outcome_tl_left_name": null,
          "outcome_type_id": 259,
          "outcome_visible": true,
          "participant_number": 1
        },
        {
          "outcome_coef": 2.13,
          "outcome_id": 2041811501,
          "outcome_name": "Николай Широков (+1.5) ",
          "outcome_param": "+1.5",
          "outcome_perc_stat": 0.0,
          "outcome_short_name": "2 (+1.5)",
          "outcome_tag": null,
          "outcome_tl_header_name": null,
          "outcome_tl_left_name": null,
          "outcome_type_id": 260,
          "outcome_visible": true,
          "participant_number": 2
        }
      ],
      "result_type_id": 83,
      "result_type_name": "4 Сет",
      "result_type_short_name": "C4",
      "result_type_weigh": 5,
      "service_id": 1,
      "sport_id": 2
    },
    {
      "event_id": 25511046,
      "market_has_param": true,
      "market_id": 784291266,
      "market_name": "Фора по геймам",
      "market_order": "06000001000100150000",
      "market_suspend": false,
      "market_template_id": 690,
      "market_template_view_id": 1,
      "market_template_view_schema": null,
      "market_template_weigh": 60,
      "outcomes": [
        {
          "outcome_coef": 1.27,
          "outcome_id": 2041811933,
          "outcome_name": "Абакар Джалилов (+1.5) ",
          "outcome_param": "+1.5",
          "outcome_perc_stat": 0.0,
          "outcome_short_name": "1 (+1.5)",
          "outcome_tag": null,
          "outcome_tl_header_name": null,
          "outcome_tl_left_name": null,
          "outcome_type_id": 259,
          "outcome_visible": true,
          "participant_number": 1
        },
        {
          "outcome_coef": 3.35,
          "outcome_id": 2041811934,
          "outcome_name": "Николай Широков (-1.5) ",
          "outcome_param": "-1.5",
          "outcome_perc_stat": 0.0,
          "outcome_short_name": "2 (-1.5)",
          "outcome_tag": null,
          "outcome_tl_header_name": null,
          "outcome_tl_left_name": null,
          "outcome_type_id": 260,
          "outcome_visible": true,
          "participant_number": 2
        }
      ],
      "result_type_id": 83,
      "result_type_name": "4 Сет",
      "result_type_short_name": "C4",
      "result_type_weigh": 5,
      "service_id": 1,
      "sport_id": 2
    },
    {
      "event_id": 25511046,
      "market_has_param": true,
      "market_id": 784289961,
      "market_name": "Тотал геймов",
      "market_order": "06500001000100850000",
      "market_suspend": false,
      "market_template_id": 560,
      "market_template_view_id": 1,
      "market_template_view_schema": null,
      "market_template_weigh": 65,
      "outcomes": [
        {
          "outcome_coef": 1.17,
          "outcome_id": 2041807666,
          "outcome_name": "Больше (8.5)",
          "outcome_param": "8.5",
          "outcome_perc_stat": 0.0,
          "outcome_short_name": "Б (8.5)",
          "outcome_tag": null,
          "outcome_tl_header_name": null,
          "outcome_tl_left_name": null,
          "outcome_type_id": 10,
          "outcome_visible": true,
          "participant_number": null
        },
        {
          "outcome_coef": 4.45,
          "outcome_id": 2041807667,
          "outcome_name": "Меньше (8.5)",
          "outcome_param": "8.5",
          "outcome_perc_stat": 0.0,
          "outcome_short_name": "М (8.5)",
          "outcome_tag": null,
          "outcome_tl_header_name": null,
          "outcome_tl_left_name": null,
          "outcome_type_id": 11,
          "outcome_visible": true,
          "participant_number": null
        }
      ],
      "result_type_id": 83,
      "result_type_name": "4 Сет",
      "result_type_short_name": "C4",
      "result_type_weigh": 5,
      "service_id": 1,
      "sport_id": 2
    },
    {
      "event_id": 25511046,
      "market_has_param": true,
      "market_id": 784289965,
      "market_name": "Тотал геймов",
      "market_order": "06500001000100950000",
      "market_suspend": false,
      "market_template_id": 560,
      "market_template_view_id": 1,
      "market_template_view_schema": null,
      "market_template_weigh": 65,
      "outcomes": [
        {
          "outcome_coef": 1.5,
          "outcome_id": 2041807668,
          "outcome_name": "Больше (9.5)",
          "outcome_param": "9.5",
          "outcome_perc_stat": 0.0,
          "outcome_short_name": "Б (9.5)",
          "outcome_tag": null,
          "outcome_tl_header_name": null,
          "outcome_tl_left_name": null,
          "outcome_type_id": 10,
          "outcome_visible": true,
          "participant_number": null
        },
        {
          "outcome_coef": 2.39,
          "outcome_id": 2041807669,
          "outcome_name": "Меньше (9.5)",
          "outcome_param": "9.5",
          "outcome_perc_stat": 0.0,
          "outcome_short_name": "М (9.5)",
          "outcome_tag": null,
          "outcome_tl_header_name": null,
          "outcome_tl_left_name": null,
          "outcome_type_id": 11,
          "outcome_visible": true,
          "participant_number": null
        }
      ],
      "result_type_id": 83,
      "result_type_name": "4 Сет",
      "result_type_short_name": "C4",
      "result_type_weigh": 5,
      "service_id": 1,
      "sport_id": 2
    },
    {
      "event_id": 25511046,
      "market_has_param": true,
      "market_id": 784289973,
      "market_name": "Тотал геймов",
      "market_order": "06500001000101050000",
      "market_suspend": false,
      "market_template_id": 560,
      "market_template_view_id": 1,
      "market_template_view_schema": null,
      "market_template_weigh": 65,
      "outcomes": [
        {
          "outcome_coef": 2.83,
          "outcome_id": 2041807670,
          "outcome_name": "Больше (10.5)",
          "outcome_param": "10.5",
          "outcome_perc_stat": 0.0,
          "outcome_short_name": "Б (10.5)",
          "outcome_tag": null,
          "outcome_tl_header_name": null,
          "outcome_tl_left_name": null,
          "outcome_type_id": 10,
          "outcome_visible": true,
          "participant_number": null
        },
        {
          "outcome_coef": 1.38,
          "outcome_id": 2041807671,
          "outcome_name": "Меньше (10.5)",
          "outcome_param": "10.5",
          "outcome_perc_stat": 0.0,
          "outcome_short_name": "М (10.5)",
          "outcome_tag": null,
          "outcome_tl_header_name": null,
          "outcome_tl_left_name": null,
          "outcome_type_id": 11,
          "outcome_visible": true,
          "participant_number": null
        }
      ],
      "result_type_id": 83,
      "result_type_name": "4 Сет",
      "result_type_short_name": "C4",
      "result_type_weigh": 5,
      "service_id": 1,
      "sport_id": 2
    },
    {
      "event_id": 25511046,
      "market_has_param": false,
      "market_id": 784289948,
      "market_name": "Количество геймов в сете",
      "market_order": "07000001000100000000",
      "market_suspend": false,
      "market_template_id": 1213,
      "market_template_view_id": 2,
      "market_template_view_schema": null,
      "market_template_weigh": 70,
      "outcomes": [
        {
          "outcome_coef": 4.45,
          "outcome_id": 2041807659,
          "outcome_name": "6-8",
          "outcome_param": "6-8",
          "outcome_perc_stat": 0.0,
          "outcome_short_name": "6-8",
          "outcome_tag": null,
          "outcome_tl_header_name": null,
          "outcome_tl_left_name": null,
          "outcome_type_id": 135,
          "outcome_visible": true,
          "participant_number": null
        },
        {
          "outcome_coef": 1.7,
          "outcome_id": 2041807660,
          "outcome_name": "9-10",
          "outcome_param": "9-10",
          "outcome_perc_stat": 0.0,
          "outcome_short_name": "9-10",
          "outcome_tag": null,
          "outcome_tl_header_name": null,
          "outcome_tl_left_name": null,
          "outcome_type_id": 623,
          "outcome_visible": true,
          "participant_number": null
        },
        {
          "outcome_coef": 2.83,
          "outcome_id": 2041807661,
          "outcome_name": "12 или больше",
          "outcome_param": "12 or more",
          "outcome_perc_stat": 0.0,
          "outcome_short_name": "12 или больше",
          "outcome_tag": null,
          "outcome_tl_header_name": null,
          "outcome_tl_left_name": null,
          "outcome_type_id": 624,
          "outcome_visible": true,
          "participant_number": null
        }
      ],
      "result_type_id": 83,
      "result_type_name": "4 Сет",
      "result_type_short_name": "C4",
      "result_type_weigh": 5,
      "service_id": 1,
      "sport_id": 2
    },
    {
      "event_id": 25511046,
      "market_has_param": true,
      "market_id": 784289936,
      "market_name": "Кто первым выиграет 2 гейма",
      "market_order": "08000001002100000000",
      "market_suspend": false,
      "market_template_id": 1191,
      "market_template_view_id": 1,
      "market_template_view_schema": null,
      "market_template_weigh": 80,
      "outcomes": [
        {
          "outcome_coef": 2.75,
          "outcome_id": 2041807643,
          "outcome_name": "Абакар Джалилов",
          "outcome_param": null,
          "outcome_perc_stat": 0.0,
          "outcome_short_name": "1",
          "outcome_tag": null,
          "outcome_tl_header_name": null,
          "outcome_tl_left_name": null,
          "outcome_type_id": 1,
          "outcome_visible": true,
          "participant_number": 1
        },
        {
          "outcome_coef": 1.36,
          "outcome_id": 2041807644,
          "outcome_name": "Николай Широков",
          "outcome_param": null,
          "outcome_perc_stat": 0.0,
          "outcome_short_name": "2",
          "outcome_tag": null,
          "outcome_tl_header_name": null,
          "outcome_tl_left_name": null,
          "outcome_type_id": 3,
          "outcome_visible": true,
          "participant_number": 2
        }
      ],
      "result_type_id": 83,
      "result_type_name": "4 Сет",
      "result_type_short_name": "C4",
      "result_type_weigh": 5,
      "service_id": 1,
      "sport_id": 2
    },
    {
      "event_id": 25511046,
      "market_has_param": true,
      "market_id": 784289937,
      "market_name": "Кто первым выиграет 3 гейма",
      "market_order": "08000001003100000000",
      "market_suspend": false,
      "market_template_id": 1191,
      "market_template_view_id": 1,
      "market_template_view_schema": null,
      "market_template_weigh": 80,
      "outcomes": [
        {
          "outcome_coef": 2.07,
          "outcome_id": 2041807645,
          "outcome_name": "Абакар Джалилов",
          "outcome_param": null,
          "outcome_perc_stat": 0.0,
          "outcome_short_name": "1",
          "outcome_tag": null,
          "outcome_tl_header_name": null,
          "outcome_tl_left_name": null,
          "outcome_type_id": 1,
          "outcome_visible": true,
          "participant_number": 1
        },
        {
          "outcome_coef": 1.63,
          "outcome_id": 2041807646,
          "outcome_name": "Николай Широков",
          "outcome_param": null,
          "outcome_perc_stat": 0.0,
          "outcome_short_name": "2",
          "outcome_tag": null,
          "outcome_tl_header_name": null,
          "outcome_tl_left_name": null,
          "outcome_type_id": 3,
          "outcome_visible": true,
          "participant_number": 2
        }
      ],
      "result_type_id": 83,
      "result_type_name": "4 Сет",
      "result_type_short_name": "C4",
      "result_type_weigh": 5,
      "service_id": 1,
      "sport_id": 2
    },
    {
      "event_id": 25511046,
      "market_has_param": true,
      "market_id": 784289938,
      "market_name": "Кто первым выиграет 4 гейма",
      "market_order": "08000001004100000000",
      "market_suspend": false,
      "market_template_id": 1191,
      "market_template_view_id": 1,
      "market_template_view_schema": null,
      "market_template_weigh": 80,
      "outcomes": [
        {
          "outcome_coef": 1.78,
          "outcome_id": 2041807647,
          "outcome_name": "Абакар Джалилов",
          "outcome_param": null,
          "outcome_perc_stat": 0.0,
          "outcome_short_name": "1",
          "outcome_tag": null,
          "outcome_tl_header_name": null,
          "outcome_tl_left_name": null,
          "outcome_type_id": 1,
          "outcome_visible": true,
          "participant_number": 1
        },
        {
          "outcome_coef": 1.86,
          "outcome_id": 2041807648,
          "outcome_name": "Николай Широков",
          "outcome_param": null,
          "outcome_perc_stat": 0.0,
          "outcome_short_name": "2",
          "outcome_tag": null,
          "outcome_tl_header_name": null,
          "outcome_tl_left_name": null,
          "outcome_type_id": 3,
          "outcome_visible": true,
          "participant_number": 2
        }
      ],
      "result_type_id": 83,
      "result_type_name": "4 Сет",
      "result_type_short_name": "C4",
      "result_type_weigh": 5,
      "service_id": 1,
      "sport_id": 2
    },
    {
      "event_id": 25511046,
      "market_has_param": true,
      "market_id": 784289939,
      "market_name": "Кто первым выиграет 5 геймов",
      "market_order": "08000001005100000000",
      "market_suspend": false,
      "market_template_id": 1191,
      "market_template_view_id": 1,
      "market_template_view_schema": null,
      "market_template_weigh": 80,
      "outcomes": [
        {
          "outcome_coef": 1.65,
          "outcome_id": 2041807649,
          "outcome_name": "Абакар Джалилов",
          "outcome_param": null,
          "outcome_perc_stat": 0.0,
          "outcome_short_name": "1",
          "outcome_tag": null,
          "outcome_tl_header_name": null,
          "outcome_tl_left_name": null,
          "outcome_type_id": 1,
          "outcome_visible": true,
          "participant_number": 1
        },
        {
          "outcome_coef": 2.06,
          "outcome_id": 2041807650,
          "outcome_name": "Николай Широков",
          "outcome_param": null,
          "outcome_perc_stat": 0.0,
          "outcome_short_name": "2",
          "outcome_tag": null,
          "outcome_tl_header_name": null,
          "outcome_tl_left_name": null,
          "outcome_type_id": 3,
          "outcome_visible": true,
          "participant_number": 2
        }
      ],
      "result_type_id": 83,
      "result_type_name": "4 Сет",
      "result_type_short_name": "C4",
      "result_type_weigh": 5,
      "service_id": 1,
      "sport_id": 2
    },
    {
      "event_id": 25511046,
      "market_has_param": false,
      "market_id": 784289976,
      "market_name": "Точный счет сета",
      "market_order": "08500001000100000000",
      "market_suspend": false,
      "market_template_id": 866,
      "market_template_view_id": 4,
      "market_template_view_schema": null,
      "market_template_weigh": 85,
      "outcomes": [
        {
          "outcome_coef": 1.0,
          "outcome_id": 2041807674,
          "outcome_name": "6:0",
          "outcome_param": "6:0",
          "outcome_perc_stat": 0.0,
          "outcome_short_name": "6:0",
          "outcome_tag": null,
          "outcome_tl_header_name": null,
          "outcome_tl_left_name": null,
          "outcome_type_id": 332,
          "outcome_visible": false,
          "participant_number": null
        },
        {
          "outcome_coef": 12.5,
          "outcome_id": 2041807675,
          "outcome_name": "6:1",
          "outcome_param": "6:1",
          "outcome_perc_stat": 0.0,
          "outcome_short_name": "6:1",
          "outcome_tag": null,
          "outcome_tl_header_name": null,
          "outcome_tl_left_name": null,
          "outcome_type_id": 333,
          "outcome_visible": true,
          "participant_number": null
        },
        {
          "outcome_coef": 6.9,
          "outcome_id": 2041807676,
          "outcome_name": "6:2",
          "outcome_param": "6:2",
          "outcome_perc_stat": 0.0,
          "outcome_short_name": "6:2",
          "outcome_tag": null,
          "outcome_tl_header_name": null,
          "outcome_tl_left_name": null,
          "outcome_type_id": 335,
          "outcome_visible": true,
          "participant_number": null
        },
        {
          "outcome_coef": 8.1,
          "outcome_id": 2041807677,
          "outcome_name": "6:3",
          "outcome_param": "6:3",
          "outcome_perc_stat": 0.0,
          "outcome_short_name": "6:3",
          "outcome_tag": null,
          "outcome_tl_header_name": null,
          "outcome_tl_left_name": null,
          "outcome_type_id": 336,
          "outcome_visible": true,
          "participant_number": null
        },
        {
          "outcome_coef": 2.93,
          "outcome_id": 2041807678,
          "outcome_name": "6:4",
          "outcome_param": "6:4",
          "outcome_perc_stat": 0.0,
          "outcome_short_name": "6:4",
          "outcome_tag": null,
          "outcome_tl_header_name": null,
          "outcome_tl_left_name": null,
          "outcome_type_id": 337,
          "outcome_visible": true,
          "participant_number": null
        },
        {
          "outcome_coef": 10.0,
          "outcome_id": 2041807679,
          "outcome_name": "7:5",
          "outcome_param": "7:5",
          "outcome_perc_stat": 0.0,
          "outcome_short_name": "7:5",
          "outcome_tag": null,
          "outcome_tl_header_name": null,
          "outcome_tl_left_name": null,
          "outcome_type_id": 338,
          "outcome_visible": true,
          "participant_number": null
        },
        {
          "outcome_coef": 6.9,
          "outcome_id": 2041807680,
          "outcome_name": "7:6",
          "outcome_param": "7:6",
          "outcome_perc_stat": 0.0,
          "outcome_short_name": "7:6",
          "outcome_tag": null,
          "outcome_tl_header_name": null,
          "outcome_tl_left_name": null,
          "outcome_type_id": 339,
          "outcome_visible": true,
          "participant_number": null
        },
        {
          "outcome_coef": 10.0,
          "outcome_id": 2041807687,
          "outcome_name": "6:7",
          "outcome_param": "6:7",
          "outcome_perc_stat": 0.0,
          "outcome_short_name": "6:7",
          "outcome_tag": null,
          "outcome_tl_header_name": null,
          "outcome_tl_left_name": null,
          "outcome_type_id": 340,
          "outcome_visible": true,
          "participant_number": null
        },
        {
          "outcome_coef": 13.0,
          "outcome_id": 2041807685,
          "outcome_name": "4:6",
          "outcome_param": "4:6",
          "outcome_perc_stat": 0.0,
          "outcome_short_name": "4:6",
          "outcome_tag": null,
          "outcome_tl_header_name": null,
          "outcome_tl_left_name": null,
          "outcome_type_id": 342,
          "outcome_visible": true,
          "participant_number": null
        },
        {
          "outcome_coef": 16.5,
          "outcome_id": 2041807686,
          "outcome_name": "5:7",
          "outcome_param": "5:7",
          "outcome_perc_stat": 0.0,
          "outcome_short_name": "5:7",
          "outcome_tag": null,
          "outcome_tl_header_name": null,
          "outcome_tl_left_name": null,
          "outcome_type_id": 341,
          "outcome_visible": true,
          "participant_number": null
        },
        {
          "outcome_coef": 6.9,
          "outcome_id": 2041807684,
          "outcome_name": "3:6",
          "outcome_param": "3:6",
          "outcome_perc_stat": 0.0,
          "outcome_short_name": "3:6",
          "outcome_tag": null,
          "outcome_tl_header_name": null,
          "outcome_tl_left_name": null,
          "outcome_type_id": 343,
          "outcome_visible": true,
          "participant_number": null
        },
        {
          "outcome_coef": 20.0,
          "outcome_id": 2041807683,
          "outcome_name": "2:6",
          "outcome_param": "2:6",
          "outcome_perc_stat": 0.0,
          "outcome_short_name": "2:6",
          "outcome_tag": null,
          "outcome_tl_header_name": null,
          "outcome_tl_left_name": null,
          "outcome_type_id": 344,
          "outcome_visible": true,
          "participant_number": null
        },
        {
          "outcome_coef": 14.0,
          "outcome_id": 2041807682,
          "outcome_name": "1:6",
          "outcome_param": "1:6",
          "outcome_perc_stat": 0.0,
          "outcome_short_name": "1:6",
          "outcome_tag": null,
          "outcome_tl_header_name": null,
          "outcome_tl_left_name": null,
          "outcome_type_id": 345,
          "outcome_visible": true,
          "participant_number": null
        },
        {
          "outcome_coef": 1.0,
          "outcome_id": 2041807681,
          "outcome_name": "0:6",
          "outcome_param": "0:6",
          "outcome_perc_stat": 0.0,
          "outcome_short_name": "0:6",
          "outcome_tag": null,
          "outcome_tl_header_name": null,
          "outcome_tl_left_name": null,
          "outcome_type_id": 346,
          "outcome_visible": false,
          "participant_number": null
        }
      ],
      "result_type_id": 83,
      "result_type_name": "4 Сет",
      "result_type_short_name": "C4",
      "result_type_weigh": 5,
      "service_id": 1,
      "sport_id": 2
    },
    {
      "event_id": 25511046,
      "market_has_param": false,
      "market_id": 784289952,
      "market_name": "Тайбрейк в сете",
      "market_order": "09000001000100000000",
      "market_suspend": false,
      "market_template_id": 440,
      "market_template_view_id": 1,
      "market_template_view_schema": null,
      "market_template_weigh": 90,
      "outcomes": [
        {
          "outcome_coef": 4.05,
          "outcome_id": 2041807664,
          "outcome_name": "Да",
          "outcome_param": null,
          "outcome_perc_stat": 0.0,
          "outcome_short_name": "Да",
          "outcome_tag": null,
          "outcome_tl_header_name": null,
          "outcome_tl_left_name": null,
          "outcome_type_id": 20,
          "outcome_visible": true,
          "participant_number": null
        },
        {
          "outcome_coef": 1.2,
          "outcome_id": 2041807665,
          "outcome_name": "Нет",
          "outcome_param": null,
          "outcome_perc_stat": 0.0,
          "outcome_short_name": "Нет",
          "outcome_tag": null,
          "outcome_tl_header_name": null,
          "outcome_tl_left_name": null,
          "outcome_type_id": 21,
          "outcome_visible": true,
          "participant_number": null
        }
      ],
      "result_type_id": 83,
      "result_type_name": "4 Сет",
      "result_type_short_name": "C4",
      "result_type_weigh": 5,
      "service_id": 1,
      "sport_id": 2
    },
    {
      "event_id": 25511046,
      "market_has_param": false,
      "market_id": 784289951,
      "market_name": "Тотал геймов Чёт / Нечет",
      "market_order": "10000001000100000000",
      "market_suspend": false,
      "market_template_id": 871,
      "market_template_view_id": 1,
      "market_template_view_schema": null,
      "market_template_weigh": 100,
      "outcomes": [
        {
          "outcome_coef": 2.15,
          "outcome_id": 2041807662,
          "outcome_name": "Нечет",
          "outcome_param": "Odd",
          "outcome_perc_stat": 0.0,
          "outcome_short_name": "Нечет",
          "outcome_tag": null,
          "outcome_tl_header_name": null,
          "outcome_tl_left_name": null,
          "outcome_type_id": 30,
          "outcome_visible": true,
          "participant_number": null
        },
        {
          "outcome_coef": 1.61,
          "outcome_id": 2041807663,
          "outcome_name": "Чет",
          "outcome_param": "Even",
          "outcome_perc_stat": 0.0,
          "outcome_short_name": "Чет",
          "outcome_tag": null,
          "outcome_tl_header_name": null,
          "outcome_tl_left_name": null,
          "outcome_type_id": 31,
          "outcome_visible": true,
          "participant_number": null
        }
      ],
      "result_type_id": 83,
      "result_type_name": "4 Сет",
      "result_type_short_name": "C4",
      "result_type_weigh": 5,
      "service_id": 1,
      "sport_id": 2
    }
  ]
}